{"categories":[{"id":"5702b88d-1e56-4ecc-9886-e8c6fa02f727","name":"MasterCard","createdAt":1645500503081,"updatedAt":1645500503081},{"id":"ce10b7ac-ed2f-464e-9796-2dd585a4f62d","name":"MasterCard","createdAt":1645500503081,"updatedAt":1645500503081},{"id":"a63eeaa0-eea8-4400-a01c-c809c8d19788","name":"American Express","createdAt":1645500503082,"updatedAt":1645500503082},{"id":"334f11b2-0fa5-450b-abb4-67d2c0b7ff76","name":"MasterCard","createdAt":1645500503082,"updatedAt":1645500503082}],"products":[{"categoryId":"5702b88d-1e56-4ecc-9886-e8c6fa02f727","id":"2345115b-8310-4ff0-bfa8-89f1e2170fea","name":"Tenetur voluptatem rerum","color":"HoneyDew","price":0.5923552759923041,"description":"Optional logistical concept","createdAt":1645500503082,"updatedAt":1645500503082,"thumbnailUrl":"http://Lola.org/"},{"categoryId":"5702b88d-1e56-4ecc-9886-e8c6fa02f727","id":"8f6c1e40-dc75-421f-a639-c5270cd3b15e","name":"Ipsam omnis","color":"MediumOrchid","price":0.5867241211235523,"description":"Object-based content-based monitoring","createdAt":1645500503082,"updatedAt":1645500503082,"thumbnailUrl":"http://www.Mertie.org/"},{"categoryId":"5702b88d-1e56-4ecc-9886-e8c6fa02f727","id":"f9715a4d-51f8-49a8-acd7-af8006744052","name":"Veritatis sequi adipisci","color":"Maroon","price":0.8641955174971372,"description":"Inverse solution-oriented productivity","createdAt":1645500503082,"updatedAt":1645500503082,"thumbnailUrl":"http://Maggio.biz/"},{"categoryId":"5702b88d-1e56-4ecc-9886-e8c6fa02f727","id":"886813a2-95f5-4863-a3bb-c2032073e183","name":"Error et perferendis","color":"LimeGreen","price":0.9603663571178913,"description":"Front-line dynamic internetsolution","createdAt":1645500503082,"updatedAt":1645500503082,"thumbnailUrl":"http://Blanda.com/"},{"categoryId":"5702b88d-1e56-4ecc-9886-e8c6fa02f727","id":"30e9720c-320c-4baa-86d6-f473dca98dff","name":"Saepe facere autem","color":"DarkGray","price":0.48742597037926316,"description":"Synergized uniform model","createdAt":1645500503082,"updatedAt":1645500503082,"thumbnailUrl":"http://www.Libby.info/"},{"categoryId":"ce10b7ac-ed2f-464e-9796-2dd585a4f62d","id":"a775e0d3-db24-4937-ad78-597a5a54d12d","name":"Delectus labore soluta","color":"DeepSkyBlue","price":0.6494352207519114,"description":"Fully-configurable intangible policy","createdAt":1645500503082,"updatedAt":1645500503082,"thumbnailUrl":"http://Colleen.io/"},{"categoryId":"ce10b7ac-ed2f-464e-9796-2dd585a4f62d","id":"b77a31f8-b150-4dff-a420-bbcd1990a7b1","name":"Aliquam asperiores","color":"Fuchsia","price":0.3331521332729608,"description":"Enterprise-wide mobile software","createdAt":1645500503082,"updatedAt":1645500503082,"thumbnailUrl":"http://Donnie.org/"},{"categoryId":"ce10b7ac-ed2f-464e-9796-2dd585a4f62d","id":"3e40682b-4cd9-40b5-8fe7-39b43cbc56ea","name":"Officiis amet","color":"Maroon","price":0.3805840366985649,"description":"Cross-group content-based productivity","createdAt":1645500503082,"updatedAt":1645500503082,"thumbnailUrl":"http://www.Gwen.co.uk/"},{"categoryId":"ce10b7ac-ed2f-464e-9796-2dd585a4f62d","id":"39fcf55e-5ce8-4f09-90a0-60b4e4a6d396","name":"Suscipit expedita alias","color":"DarkCyan","price":0.8664445204194635,"description":"Multi-tiered user-facing emulation","createdAt":1645500503083,"updatedAt":1645500503083,"thumbnailUrl":"http://www.Padberg.name/"},{"categoryId":"ce10b7ac-ed2f-464e-9796-2dd585a4f62d","id":"d3934974-4b72-4519-9f58-453ea734c38b","name":"Voluptas ducimus","color":"Pink","price":0.5293748178519309,"description":"Organic bi-directional installation","createdAt":1645500503083,"updatedAt":1645500503083,"thumbnailUrl":"http://www.Jeanette.biz/"},{"categoryId":"a63eeaa0-eea8-4400-a01c-c809c8d19788","id":"1e069ac9-aa94-4a7c-b078-6b800555bb0a","name":"Earum ab","color":"DarkGoldenRod","price":0.5493365076836199,"description":"Inverse solution-oriented moderator","createdAt":1645500503083,"updatedAt":1645500503083,"thumbnailUrl":"http://www.Conn.org/"},{"categoryId":"a63eeaa0-eea8-4400-a01c-c809c8d19788","id":"b888fa18-650f-4a47-865f-21fae1a5dd4b","name":"Beatae quidem sint","color":"DarkBlue","price":0.7432275558821857,"description":"Customizable didactic benchmark","createdAt":1645500503083,"updatedAt":1645500503083,"thumbnailUrl":"http://Darby.name/"},{"categoryId":"a63eeaa0-eea8-4400-a01c-c809c8d19788","id":"6bc53588-5211-46b6-8d1c-980b55081f23","name":"Et et dolorum","color":"Tan","price":0.8922841283492744,"description":"Ergonomic interactive encoding","createdAt":1645500503083,"updatedAt":1645500503083,"thumbnailUrl":"http://Adams.us/"},{"categoryId":"a63eeaa0-eea8-4400-a01c-c809c8d19788","id":"4159ee73-6e64-4180-8c82-a0d3671d58d9","name":"Totam est","color":"MidnightBlue","price":0.22538206726312637,"description":"Programmable grid-enabled opensystem","createdAt":1645500503083,"updatedAt":1645500503083,"thumbnailUrl":"http://www.Kacie.org/"},{"categoryId":"a63eeaa0-eea8-4400-a01c-c809c8d19788","id":"f6af5189-3483-4417-ae8e-7e085d2ebea1","name":"Aut magni provident","color":"MediumOrchid","price":0.9951794368680567,"description":"Implemented mobile customerloyalty","createdAt":1645500503083,"updatedAt":1645500503083,"thumbnailUrl":"http://Zander.net/"},{"categoryId":"334f11b2-0fa5-450b-abb4-67d2c0b7ff76","id":"52deff50-e774-4cb2-9696-81ff11c1940e","name":"Ut repellendus","color":"MistyRose","price":0.5790219309274107,"description":"Diverse client-server product","createdAt":1645500503083,"updatedAt":1645500503083,"thumbnailUrl":"http://www.Marks.name/"},{"categoryId":"334f11b2-0fa5-450b-abb4-67d2c0b7ff76","id":"9bd33bd2-3af8-46cd-981d-a8d48d787017","name":"Eum rerum quia","color":"DarkOliveGreen","price":0.9064996389206499,"description":"Re-engineered multimedia access","createdAt":1645500503084,"updatedAt":1645500503084,"thumbnailUrl":"http://Everett.io/"},{"categoryId":"334f11b2-0fa5-450b-abb4-67d2c0b7ff76","id":"bbb2f729-79e9-40cd-aaa2-90bcc427a075","name":"Est aliquid","color":"GhostWhite","price":0.640703595476225,"description":"Profound modular opensystem","createdAt":1645500503084,"updatedAt":1645500503084,"thumbnailUrl":"http://www.Lockman.name/"},{"categoryId":"334f11b2-0fa5-450b-abb4-67d2c0b7ff76","id":"2dffb8ba-2ade-4612-a2cb-b87518036970","name":"Similique minima est","color":"Magenta","price":0.011463712900876999,"description":"Cloned holistic knowledgeuser","createdAt":1645500503084,"updatedAt":1645500503084,"thumbnailUrl":"http://Hauck.us/"},{"categoryId":"334f11b2-0fa5-450b-abb4-67d2c0b7ff76","id":"5986e430-c72c-4bdd-b887-67fa4d29aa8c","name":"Optio sed","color":"Orange","price":0.03169943345710635,"description":"Balanced global installation","createdAt":1645500503084,"updatedAt":1645500503084,"thumbnailUrl":"http://www.Greenfelder.ca/"}],"profile":{"name":"Po"}}